example/__init__.py
example/cli.py
plugin_cli/__init__.py
plugin_cli/args_parser/__init__.py
plugin_cli/args_parser/args_parser.py
plugin_cli/args_parser/cli_description.py
plugin_cli/base/__init__.py
plugin_cli/base/result.py
plugin_cli/plugin/__init__.py
plugin_cli/plugin/plugin.py
plugin_cli/plugin/plugin_manager.py
plugin_cli-0.0.4.dist-info/LICENSE
plugin_cli-0.0.4.dist-info/METADATA
plugin_cli-0.0.4.dist-info/WHEEL
plugin_cli-0.0.4.dist-info/top_level.txt
plugin_cli-0.0.4.dist-info/RECORD
