Metadata-Version: 2.1
Name: plugin-cli
Version: 0.0.4
Summary: Rapidly Build a Plugin-Based CLI Tool Framework
Home-page: https://gitee.com/zhaosong-lmm_admin/cli-framework
Author: Song Zhao
Author-email: zhaosonggo@163.com
Classifier: Programming Language :: Python :: 3
Classifier: License :: OSI Approved :: Apache Software License
Classifier: Operating System :: OS Independent
License-File: LICENSE
